CHANGES.txt
LICENSE.txt
MANIFEST.in
README.md
requirements-dev.txt
requirements.txt
setup.py
rtmp2img/__init__.py
rtmp2img/cli.py
rtmp2img/lib.py
rtmp2img.egg-info/PKG-INFO
rtmp2img.egg-info/SOURCES.txt
rtmp2img.egg-info/dependency_links.txt
rtmp2img.egg-info/entry_points.txt
rtmp2img.egg-info/not-zip-safe
rtmp2img.egg-info/requires.txt
rtmp2img.egg-info/top_level.txt