Metadata-Version: 1.0
Name: rtmp2img
Version: 0.1.4
Summary: Save images from rtmp live videos
Home-page: https://github.com/globocom/rtmp2img
Author: Globo.com
Author-email: UNKNOWN
License: UNKNOWN
Platform: UNKNOWN
